{
    "repos": [
        {
            "name": "BigBoss",
            "clickLink": "http://apt.thebigboss.org/repofiles/cydia/ stable main",
            "url": "http://apt.thebigboss.org/repofiles/cydia/",
            "icon": "http://apt.thebigboss.org/repofiles/cydia/dists/stable/CydiaIcon.png"
        },
        {
            "name": "Chariz",
            "clickLink": "https://repo.chariz.io/",
            "url": "https://repo.chariz.io/",
            "icon": "https://repo.chariz.io/CydiaIcon.png"
        },
        {
            "name": "Dynastic Repo",
            "clickLink": "https://repo.dynastic.co/",
            "url": "https://repo.dynastic.co/",
            "icon": "https://repo.dynastic.co/CydiaIcon.png"
        },
        {
            "name": "ModMyi (Archive)",
            "clickLink": "http://apt.modmyi.com/ stable main",
            "url": "http://apt.modmyi.com/",
            "icon": "http://apt.modmyi.com/dists/stable/CydiaIcon.png"
        },
        {
            "name": "Nepeta",
            "clickLink": "https://repo.nepeta.me/",
            "url": "https://repo.nepeta.me/",
            "icon": "https://repo.nepeta.me/CydiaIcon.png"
        },
        {
            "name": "Packix",
            "clickLink": "https://repo.packix.com/",
            "url": "https://repo.packix.com/",
            "icon": "https://repo.packix.com/CydiaIcon.png"
        },
        {
            "name": "ZodTTD & MacCiti (Archive)",
            "clickLink": "http://cydia.zodttd.com/repo/cydia/ stable main",
            "url": "http://cydia.zodttd.com/repo/cydia/",
            "icon": "http://cydia.zodttd.com/repo/cydia/dists/stable/CydiaIcon.png"
        }
    ]
}
